{
  "meta": {
    "version": "1.0.0",
    "description": "Size buckets by species with weight ranges in kg"
  },
  "dog": {
    "toy": {
      "minKg": 0.0,
      "maxKg": 5.0,
      "en": "Toy",
      "bg": "Играчка"
    },
    "small": {
      "minKg": 5.0,
      "maxKg": 11.0,
      "en": "Small",
      "bg": "Малко"
    },
    "medium": {
      "minKg": 11.0,
      "maxKg": 27.0,
      "en": "Medium",
      "bg": "Средно"
    },
    "large": {
      "minKg": 27.0,
      "maxKg": 45.0,
      "en": "Large",
      "bg": "Голямо"
    },
    "giant": {
      "minKg": 45.0,
      "maxKg": null,
      "en": "Giant",
      "bg": "Гигантско"
    }
  },
  "cat": {
    "small": {
      "minKg": 0.0,
      "maxKg": 4.0,
      "en": "Small",
      "bg": "Малка"
    },
    "medium": {
      "minKg": 4.0,
      "maxKg": 7.0,
      "en": "Medium",
      "bg": "Средна"
    },
    "large": {
      "minKg": 7.0,
      "maxKg": null,
      "en": "Large",
      "bg": "Голяма"
    }
  }
}

